galaxy_update/__init__.py
galaxy_update/__main__.py
galaxy_update/cli.py
galaxy_update-1.0.0.dist-info/METADATA
galaxy_update-1.0.0.dist-info/WHEEL
galaxy_update-1.0.0.dist-info/entry_points.txt
galaxy_update-1.0.0.dist-info/licenses/LICENSE
galaxy_update-1.0.0.dist-info/RECORD
