Metadata-Version: 2.4
Name: galaxy-update
Version: 1.0.0
Summary: Update dependencies in requirements.yml
Project-URL: Repository, https://github.com/deadnews/galaxy-update
Project-URL: Changelog, https://github.com/deadnews/galaxy-update/CHANGELOG.md
Author-email: deadnews <deadnewsgit@gmail.com>
License-Expression: MIT
License-File: LICENSE
Keywords: ansible,ansible-galaxy ,galaxy,requirements
Classifier: Operating System :: OS Independent
Requires-Python: >=3.10
Requires-Dist: click>=8.1.7
Requires-Dist: httpx>=0.28.0
Requires-Dist: pyaml>=25.5.0
Requires-Dist: pyyaml>=6.0.2
